azure_tts_client/__init__.py
azure_tts_client/__main__.py
azure_tts_client-0.1.2.dist-info/METADATA
azure_tts_client-0.1.2.dist-info/WHEEL
azure_tts_client-0.1.2.dist-info/entry_points.txt
azure_tts_client-0.1.2.dist-info/RECORD
