Metadata-Version: 2.4
Name: azure-tts-client
Version: 0.1.2
Summary: Azure Text-to-Speech Terminal Client
Author-email: Steins Z <steins.z@foxmail.com>
Keywords: azure,cli,speech-synthesis,terminal,text-to-speech,tts
Classifier: Development Status :: 3 - Alpha
Classifier: Intended Audience :: Developers
Classifier: License :: OSI Approved :: MIT License
Classifier: Programming Language :: Python :: 3
Classifier: Programming Language :: Python :: 3.14
Requires-Python: >=3.14
Requires-Dist: azure-cognitiveservices-speech>=1.46.0
Requires-Dist: textual>=6.3.0
